setup.py
submit_k8s_job
k8s/__init__.py
k8s/comm.py
k8s/parser.py
k8s/schema.py
k8s_helper.egg-info/PKG-INFO
k8s_helper.egg-info/SOURCES.txt
k8s_helper.egg-info/dependency_links.txt
k8s_helper.egg-info/requires.txt
k8s_helper.egg-info/top_level.txt