Metadata-Version: 1.0
Name: k8s-helper
Version: 0.1.0
Summary: CLI to send and wait for jobs to a Kubernetes cluster, requires a working kubectl (can connect to the desired K8s cluster) on the machine running this code.
Home-page: https://github.com/phnmnl/k8s-helper
Author: Pablo Moreno, Pierrick Roger Mele
Author-email: phenomenal-h2020-users@googlegroups.com
License: Apache 2.0
Platform: UNKNOWN
